ledgerify/ledgerify.py
ledgerify-0.2.2.dist-info/LICENSE
ledgerify-0.2.2.dist-info/METADATA
ledgerify-0.2.2.dist-info/WHEEL
ledgerify-0.2.2.dist-info/entry_points.txt
ledgerify-0.2.2.dist-info/RECORD
