Metadata-Version: 2.1
Name: ledgerify
Version: 0.2.2
Summary: Ledger transactions importer
License: GPL-3.0
Author: Michal Goral
Author-email: dev@goral.net.pl
Requires-Python: >=3.10,<4.0
Classifier: License :: OSI Approved :: GNU General Public License v3 (GPLv3)
Classifier: Programming Language :: Python :: 3
Classifier: Programming Language :: Python :: 3.10
Classifier: Programming Language :: Python :: 3.11
Classifier: Programming Language :: Python :: 3.12
